lookout_cli/__init__.py
lookout_cli/auth_helpers.py
lookout_cli/banner.py
lookout_cli/cli.py
lookout_cli/helpers.py
lookout_cli/docker/docker-compose.cache.yaml
lookout_cli/docker/docker-compose.dev.yaml
lookout_cli/docker/docker-compose.jetson.yaml
lookout_cli/docker/docker-compose.network-host.yaml
lookout_cli/docker/docker-compose.network-proxy.yaml
lookout_cli/docker/docker-compose.prod.yaml
lookout_cli/docker/docker-compose.yaml
lookout_cli/groups/__init__.py
lookout_cli/groups/base.py
lookout_cli/groups/model.py
lookout_cli/groups/setup.py
lookout_cli/test/lookout_cli_test.py
lookout_cli-3.0.1.dist-info/METADATA
lookout_cli-3.0.1.dist-info/WHEEL
lookout_cli-3.0.1.dist-info/entry_points.txt
lookout_cli-3.0.1.dist-info/top_level.txt
lookout_cli-3.0.1.dist-info/zip-safe
lookout_cli-3.0.1.dist-info/RECORD
