Metadata-Version: 2.4
Name: lookout_cli
Version: 3.0.1
Summary: A CLI for interacting with Lookout+
Author-email: Greenroom Robotics <team@greenroomrobotics.com>
Maintainer-email: David Revay <david.revay@greenroomrobotics.com>
License: Copyright (C) 2025, Greenroom Robotics
Project-URL: homepage, https://github.com/Greenroom-Robotics/lookout
Keywords: colcon
Classifier: Development Status :: 3 - Alpha
Classifier: Environment :: Plugins
Classifier: Intended Audience :: Developers
Classifier: Programming Language :: Python
Classifier: Topic :: Software Development :: Build Tools
Requires-Dist: toml~=0.10
Requires-Dist: setuptools
Requires-Dist: colorama
Requires-Dist: click
Requires-Dist: lookout-config
Requires-Dist: python-on-whales
Requires-Dist: PyYAML
Requires-Dist: bcrypt
Requires-Dist: mlflow-skinny<3,>=2.19.0
